LICENSE
README.md
setup.cfg
setup.py
oddsgym/__init__.py
oddsgym.egg-info/PKG-INFO
oddsgym.egg-info/SOURCES.txt
oddsgym.egg-info/dependency_links.txt
oddsgym.egg-info/entry_points.txt
oddsgym.egg-info/requires.txt
oddsgym.egg-info/top_level.txt
oddsgym/envs/__init__.py
oddsgym/envs/base.py
oddsgym/envs/base_percentage.py
oddsgym/envs/daily_bets.py
oddsgym/envs/footballdata.py
oddsgym/envs/meta.py
oddsgym/envs/soccer.py
oddsgym/envs/tennis.py
oddsgym/envs/tennisdata.py
oddsgym/utils/__init__.py
oddsgym/utils/csv_downloader.py
oddsgym/utils/constants/__init__.py
oddsgym/utils/constants/football.py
oddsgym/utils/constants/tennis.py
tests/test_base_env.py
tests/test_base_percentage_env.py
tests/test_csv_downloader.py
tests/test_daily_env.py
tests/test_daily_percentage_env.py
tests/test_footballdata_env.py
tests/test_integration_with_rllib.py
tests/test_integration_with_stable_baselines.py
tests/test_integration_with_stable_baselines_v3.py
tests/test_tennis_daily_env.py
tests/test_tennis_daily_percentage_env.py
tests/test_tennis_env.py
tests/test_tennis_percentage_env.py
tests/test_tennisdata_env.py
tests/test_three_way_daily_env.py
tests/test_three_way_daily_percentage_env.py
tests/test_three_way_env.py
tests/test_three_way_percentage_env.py