Metadata-Version: 2.1
Name: oddsgym
Version: 0.8.3
Summary: A sports betting environment for OpenAI Gym
Home-page: https://github.com/OryJonay/Odds-Gym
Author: Ory Jonay
Author-email: kriegsmeister@gmail.com
Requires-Python: >=3.6
License-File: LICENSE
Requires-Dist: gymnasium
Requires-Dist: more-itertools
Requires-Dist: pandas
Requires-Dist: numexpr
Requires-Dist: tabulate
Requires-Dist: aiohttp
Requires-Dist: typer
Requires-Dist: infi.traceback
Provides-Extra: examples
Requires-Dist: jupyter; extra == "examples"
Requires-Dist: notebook; extra == "examples"
Requires-Dist: stable-baselines; extra == "examples"
Provides-Extra: tests
Requires-Dist: pytest; extra == "tests"
Requires-Dist: pytest-cov; extra == "tests"
Requires-Dist: coveralls; extra == "tests"
Provides-Extra: docs
Requires-Dist: Sphinx; extra == "docs"
Requires-Dist: sphinx-rtd-theme; extra == "docs"
Provides-Extra: integration
Requires-Dist: stable-baselines[mpi]; extra == "integration"
Requires-Dist: stable-baselines3[extra]; extra == "integration"
Requires-Dist: tensorflow<=1.15.2; extra == "integration"
Requires-Dist: ray[rllib]; extra == "integration"
